pricestf/__init__.py
pricestf/itemids.json
pricestf/pricestf.py
pricestf-1.0.7.dist-info/LICENSE
pricestf-1.0.7.dist-info/METADATA
pricestf-1.0.7.dist-info/WHEEL
pricestf-1.0.7.dist-info/top_level.txt
pricestf-1.0.7.dist-info/RECORD
